telegram_framework/__init__.py
telegram_framework/__main__.py
telegram_framework/_version.py
telegram_framework/shortcuts.py
telegram_framework/conf/__init__.py
telegram_framework/conf/default_settings.py
telegram_framework/conf/utils.py
telegram_framework/core/__init__.py
telegram_framework/core/app.py
telegram_framework/core/decorators.py
telegram_framework/core/module.py
telegram_framework/exceptions/__init__.py
telegram_framework/management/__init__.py
telegram_framework/management/base.py
telegram_framework/management/templates.py
telegram_framework/management/commands/__init__.py
telegram_framework/management/commands/clearenv.py
telegram_framework/management/commands/createmodule.py
telegram_framework/management/commands/startproject.py
telegram_framework/templates/module_template/__init__.py
telegram_framework/templates/module_template/handlers.py
telegram_framework/templates/module_template/models.py
telegram_framework/templates/project_template/.gitignore
telegram_framework/templates/project_template/__init__.py
telegram_framework/templates/project_template/app.py
telegram_framework/templates/project_template/manage.py
telegram_framework/templates/project_template/models.py
telegram_framework/templates/project_template/settings.py
telegram_framework/templates/project_template/resources/assets/readme
telegram_framework/templates/project_template/resources/lang/README
telegram_framework/templates/project_template/resources/templates/README
telegram_framework/utils/__init__.py
telegram_framework/utils/functional.py
telegram_framework/utils/version.py
python_telegram_framework-1.0.0.dist-info/LICENSE
python_telegram_framework-1.0.0.dist-info/METADATA
python_telegram_framework-1.0.0.dist-info/WHEEL
python_telegram_framework-1.0.0.dist-info/entry_points.txt
python_telegram_framework-1.0.0.dist-info/top_level.txt
python_telegram_framework-1.0.0.dist-info/RECORD
