Metadata-Version: 2.1
Name: python-telegram-framework
Version: 1.0.0
Summary: Small framework to create bots with python-telegram-bot
Author-email: Víctor Martínez Amador <vmartineza33@gmail.com>
License: MIT License
Project-URL: Repository, https://github.com/vmartinez33/python-telegram-framework
Project-URL: Documentation, https://vmartinez33.github.io/python-telegram-framework/
Keywords: telegram,bot,framework
Classifier: Development Status :: 3 - Alpha
Classifier: Programming Language :: Python :: 3
Classifier: License :: OSI Approved :: MIT License
Classifier: Operating System :: OS Independent
Requires-Python: >=3.8
License-File: LICENSE
Requires-Dist: packaging
Requires-Dist: python-telegram-bot[all]
Requires-Dist: pyngrok
